{
  "root_group": {
    "name": "",
    "path": "",
    "id": "d41d8cd98f00b204e9800998ecf8427e",
    "groups": [],
    "checks": [
        {
          "name": "status is 200",
          "path": "::status is 200",
          "id": "6210a8cd14cd70477eba5c5e4cb3fb5f",
          "passes": 15000,
          "fails": 0
        }
      ]
  },
  "options": {
    "summaryTimeUnit": "",
    "noColor": false,
    "summaryTrendStats": [
      "avg",
      "min",
      "med",
      "max",
      "p(90)",
      "p(95)"
    ]
  },
  "state": {
    "isStdOutTTY": false,
    "isStdErrTTY": false,
    "testRunDurationMs": 29984.778743
  },
  "metrics": {
    "http_req_failed": {
      "contains": "default",
      "values": {
        "rate": 0,
        "passes": 0,
        "fails": 15000
      },
      "type": "rate"
    },
    "http_req_waiting": {
      "type": "trend",
      "contains": "time",
      "values": {
        "avg": 1.5038862210000028,
        "min": 0,
        "med": 1.3769684999999998,
        "max": 25.137419,
        "p(90)": 1.9161918,
        "p(95)": 2.1663141500000003
      }
    },
    "http_reqs": {
      "type": "counter",
      "contains": "default",
      "values": {
        "count": 15000,
        "rate": 500.25381639682024
      }
    },
    "checks": {
      "type": "rate",
      "contains": "default",
      "values": {
        "rate": 1,
        "passes": 15000,
        "fails": 0
      }
    },
    "http_req_duration": {
      "type": "trend",
      "contains": "time",
      "values": {
        "p(90)": 2.0946466000000004,
        "p(95)": 2.3550530999999997,
        "avg": 1.631997671133332,
        "min": 0.104552,
        "med": 1.497447,
        "max": 25.364753
      }
    },
    "http_req_duration{expected_response:true}": {
      "type": "trend",
      "contains": "time",
      "values": {
        "avg": 1.631997671133332,
        "min": 0.104552,
        "med": 1.497447,
        "max": 25.364753,
        "p(90)": 2.0946466000000004,
        "p(95)": 2.3550530999999997
      }
    },
    "http_req_connecting": {
      "type": "trend",
      "contains": "time",
      "values": {
        "max": 0.617108,
        "p(90)": 0,
        "p(95)": 0,
        "avg": 0.0003396934,
        "min": 0,
        "med": 0
      }
    },
    "vus_max": {
      "type": "gauge",
      "contains": "default",
      "values": {
        "value": 20,
        "min": 20,
        "max": 20
      }
    },
    "http_req_sending": {
      "type": "trend",
      "contains": "time",
      "values": {
        "min": 0.006433,
        "med": 0.0391575,
        "max": 0.72295,
        "p(90)": 0.0644561,
        "p(95)": 0.07971144999999996,
        "avg": 0.03878873939999992
      }
    },
    "success_rate": {
      "type": "rate",
      "contains": "default",
      "values": {
        "rate": 1,
        "passes": 15000,
        "fails": 0
      }
    },
    "data_received": {
      "type": "counter",
      "contains": "data",
      "values": {
        "count": 13650009,
        "rate": 455231.27307339624
      }
    },
    "http_req_blocked": {
      "type": "trend",
      "contains": "time",
      "values": {
        "min": 0.002669,
        "med": 0.0050425,
        "max": 4.101195,
        "p(90)": 0.0084002,
        "p(95)": 0.010391099999999999,
        "avg": 0.007198135600000019
      }
    },
    "http_req_receiving": {
      "type": "trend",
      "contains": "time",
      "values": {
        "avg": 0.08932271073333323,
        "min": 0.015881,
        "med": 0.0694375,
        "max": 1.68401,
        "p(90)": 0.1479621,
        "p(95)": 0.18837275
      }
    },
    "vus": {
      "type": "gauge",
      "contains": "default",
      "values": {
        "value": 1,
        "min": 0,
        "max": 2
      }
    },
    "data_sent": {
      "contains": "data",
      "values": {
        "count": 1455000,
        "rate": 48524.620190491565
      },
      "type": "counter"
    },
    "iterations": {
      "values": {
        "count": 15000,
        "rate": 500.25381639682024
      },
      "type": "counter",
      "contains": "default"
    },
    "http_req_tls_handshaking": {
      "type": "trend",
      "contains": "time",
      "values": {
        "med": 0,
        "max": 0,
        "p(90)": 0,
        "p(95)": 0,
        "avg": 0,
        "min": 0
      }
    },
    "iteration_duration": {
      "type": "trend",
      "contains": "time",
      "values": {
        "max": 25.581125,
        "p(90)": 2.2849305,
        "p(95)": 2.5668874499999994,
        "avg": 1.7727165944666652,
        "min": 1.157437,
        "med": 1.6257085
      }
    }
  }
}